{
    "GDG PCE": [
      {
        "name": "Crypto Price Tracker",
        "description": "A React app that tracks cryptocurrency prices using the CoinGecko API.",
        "topics": ["hacktoberfest"],
        "languages": ["JavaScript"],
        "url": "http://github.com/gdg-pce/crypto-price-tracker"
      },
      {
        "name": "DSA Challenges 2024",
        "description": "A repository containing data structure and algorithm challenges for 2024.",
        "topics": ["hacktoberfest"],
        "languages": [],
        "url": "http://github.com/gdg-pce/DSA-Challenges-2024"
      },
      {
        "name": "Graphic Design 2024",
        "description": "Graphic design-related projects for Hacktoberfest 2024.",
        "topics": ["hacktoberfest"],
        "languages": [],
        "url": "http://github.com/gdg-pce/Graphic-Design-2024"
      },
      {
        "name": "NewsApp",
        "description": "A news application built for Hacktoberfest 2024.",
        "topics": ["hacktoberfest"],
        "languages": [],
        "url": "http://github.com/gdg-pce/NewsApp"
      },
      {
        "name": "Badge Card Generator",
        "description": "A project to generate badge cards for contributors.",
        "topics": ["hacktoberfest"],
        "languages": [],
        "url": "http://github.com/gdg-pce/BadgeCardGenerator"
      }
    ],
    "Other Open Source Projects":[
       
          {
            "name": "airbnb",
            "description": "JavaScript Style Guide",
            "topics": ["hacktoberfest"],
            "languages": ["ES5(Deprecated),React, CSS-in-JS, CSS and SASS, Ruby"],
            "url": "https://github.com/airbnb/javascript"
          },
          {
            "name": "DocsGPT",
            "description": "GPT-powered chat for documentation, chat with your documents(Flask App)",
            "topics": ["hacktoberfest"],
            "languages": ["Vite, React"],
            "url": "https://github.com/arc53/DocsGPT"
          },
          {
            "name": "Web-Dev",
            "description": "A web development project for beginners",
            "topics": ["hacktoberfest"],
            "languages": ["HTML,CSS,JavaScript"],
            "url": "https://github.com/microsoft/Web-Dev-For-Beginners"
          },
          {
            "name": "Gradio",
            "description": "Build and share delightful machine learning apps",
            "topics": ["hacktoberfest"],
            "languages": ["Python, FastAPI,PNpM, SVELTE, Vite, Storybook, tailwindcss"],
            "url": "https://github.com/gradio-app/gradio"
          },
          {
            "name": "dstack",
            "description": "An alternative to kubernates, to simplify development, training and deployment of AI across any cloud or on prem",
            "topics": ["hacktoberfest"],
            "languages": ["Postgres, backend, frontend"],
            "url": "https://github.com/dstackai/dstack"
          },
          {
            "name": "Wren AI",
            "description": "Open source SQL AI agent for Text-to-SQL",
            "topics": ["hacktoberfest"],
            "languages": ["SQL"],
            "url": "https://github.com/Canner/WrenAI"
          },
          {
            "name": "tolgee-platform",
            "description": "Developer and translator friendly web-based localization platform",
            "topics": ["hacktoberfest"],
            "languages": ["React, Angular, Vue, Svelte, Next.js, Figma plugin, i18next, Vanilla js, Unreal Engine, Rest API"],
            "url": "https://github.com/tolgee/tolgee-platform"
          },
          {
            "name": "ToolJet",
            "description": "Low-code platform for building business appplications",
            "topics": ["hacktoberfest"],
            "languages": ["JavaScript, Python"],
            "url": "https://github.com/ToolJet/ToolJet"
          },
          {
            "name": "first-contributors",
            "description": "A project for beginners",
            "topics": ["hacktoberfest"],
            "languages": ["HTML,CSS,JavaScript"],
            "url": "https://github.com/firstcontributions/first-contributions"
          }
        
    ]
  }
  